[{"id":11473,"name":"Cocobeach","state":{"id":1206},"country":{"id":82,"isocode2":"GA"}},{"id":11474,"name":"Kango","state":{"id":1206},"country":{"id":82,"isocode2":"GA"}},{"id":11475,"name":"Libreville","state":{"id":1206},"country":{"id":82,"isocode2":"GA"}},{"id":11476,"name":"Nkan","state":{"id":1206},"country":{"id":82,"isocode2":"GA"}},{"id":11477,"name":"Ntoum","state":{"id":1206},"country":{"id":82,"isocode2":"GA"}},{"id":11478,"name":"Lekoni","state":{"id":1207},"country":{"id":82,"isocode2":"GA"}},{"id":11479,"name":"Masuku","state":{"id":1207},"country":{"id":82,"isocode2":"GA"}},{"id":11480,"name":"Moanda","state":{"id":1207},"country":{"id":82,"isocode2":"GA"}},{"id":11481,"name":"Mounana","state":{"id":1207},"country":{"id":82,"isocode2":"GA"}},{"id":11482,"name":"Okandja","state":{"id":1207},"country":{"id":82,"isocode2":"GA"}},{"id":11483,"name":"Lambarene","state":{"id":1208},"country":{"id":82,"isocode2":"GA"}},{"id":11484,"name":"Ndjole","state":{"id":1208},"country":{"id":82,"isocode2":"GA"}},{"id":11485,"name":"Fougamou","state":{"id":1209},"country":{"id":82,"isocode2":"GA"}},{"id":11486,"name":"Mbigou","state":{"id":1209},"country":{"id":82,"isocode2":"GA"}},{"id":11487,"name":"Mimongo","state":{"id":1209},"country":{"id":82,"isocode2":"GA"}},{"id":11488,"name":"Mouila","state":{"id":1209},"country":{"id":82,"isocode2":"GA"}},{"id":11489,"name":"Ndende","state":{"id":1209},"country":{"id":82,"isocode2":"GA"}},{"id":11490,"name":"Mayumba","state":{"id":1210},"country":{"id":82,"isocode2":"GA"}},{"id":11491,"name":"Tchibanga","state":{"id":1210},"country":{"id":82,"isocode2":"GA"}},{"id":11492,"name":"Tsogni","state":{"id":1210},"country":{"id":82,"isocode2":"GA"}},{"id":11493,"name":"Booue","state":{"id":1211},"country":{"id":82,"isocode2":"GA"}},{"id":11494,"name":"Makokou","state":{"id":1211},"country":{"id":82,"isocode2":"GA"}},{"id":11495,"name":"Mekambo","state":{"id":1211},"country":{"id":82,"isocode2":"GA"}},{"id":11496,"name":"Koulamoutou","state":{"id":1212},"country":{"id":82,"isocode2":"GA"}},{"id":11497,"name":"Lastoursville","state":{"id":1212},"country":{"id":82,"isocode2":"GA"}},{"id":11498,"name":"Gamba","state":{"id":1213},"country":{"id":82,"isocode2":"GA"}},{"id":11499,"name":"Omboue","state":{"id":1213},"country":{"id":82,"isocode2":"GA"}},{"id":11500,"name":"Port-Gentil","state":{"id":1213},"country":{"id":82,"isocode2":"GA"}},{"id":11501,"name":"Sette Cama","state":{"id":1213},"country":{"id":82,"isocode2":"GA"}},{"id":11502,"name":"Bitam","state":{"id":1214},"country":{"id":82,"isocode2":"GA"}},{"id":11503,"name":"Lalara","state":{"id":1214},"country":{"id":82,"isocode2":"GA"}},{"id":11504,"name":"Medouneu","state":{"id":1214},"country":{"id":82,"isocode2":"GA"}},{"id":11505,"name":"Minvoul","state":{"id":1214},"country":{"id":82,"isocode2":"GA"}},{"id":11506,"name":"Mitzic","state":{"id":1214},"country":{"id":82,"isocode2":"GA"}},{"id":11507,"name":"Oyem","state":{"id":1214},"country":{"id":82,"isocode2":"GA"}}]