[{"id":17636,"name":"Baghmara","state":{"id":1570},"country":{"id":105,"isocode2":"IN"}},{"id":17637,"name":"Cherrapunji","state":{"id":1570},"country":{"id":105,"isocode2":"IN"}},{"id":17638,"name":"Jawai","state":{"id":1570},"country":{"id":105,"isocode2":"IN"}},{"id":17639,"name":"Madanrting","state":{"id":1570},"country":{"id":105,"isocode2":"IN"}},{"id":17640,"name":"Mairang","state":{"id":1570},"country":{"id":105,"isocode2":"IN"}},{"id":17641,"name":"Mawlai","state":{"id":1570},"country":{"id":105,"isocode2":"IN"}},{"id":17642,"name":"Nongmynsong","state":{"id":1570},"country":{"id":105,"isocode2":"IN"}},{"id":17643,"name":"Nongpoh","state":{"id":1570},"country":{"id":105,"isocode2":"IN"}},{"id":17644,"name":"Nongstoin","state":{"id":1570},"country":{"id":105,"isocode2":"IN"}},{"id":17645,"name":"Nongthymmai","state":{"id":1570},"country":{"id":105,"isocode2":"IN"}},{"id":17646,"name":"Pynthorumkhrah","state":{"id":1570},"country":{"id":105,"isocode2":"IN"}},{"id":17647,"name":"Resubelpara","state":{"id":1570},"country":{"id":105,"isocode2":"IN"}},{"id":17648,"name":"Shillong","state":{"id":1570},"country":{"id":105,"isocode2":"IN"}},{"id":17649,"name":"Shillong Cantonment","state":{"id":1570},"country":{"id":105,"isocode2":"IN"}},{"id":17650,"name":"Tura","state":{"id":1570},"country":{"id":105,"isocode2":"IN"}},{"id":17651,"name":"Williamnagar","state":{"id":1570},"country":{"id":105,"isocode2":"IN"}}]