[{"id":7529,"name":"Buenavista","state":{"id":741},"country":{"id":52,"isocode2":"CO"}},{"id":7530,"name":"Caimito","state":{"id":741},"country":{"id":52,"isocode2":"CO"}},{"id":7531,"name":"Chalan","state":{"id":741},"country":{"id":52,"isocode2":"CO"}},{"id":7532,"name":"Coloso","state":{"id":741},"country":{"id":52,"isocode2":"CO"}},{"id":7533,"name":"Corozal","state":{"id":741},"country":{"id":52,"isocode2":"CO"}},{"id":7534,"name":"El Roble","state":{"id":741},"country":{"id":52,"isocode2":"CO"}},{"id":7535,"name":"Galeras","state":{"id":741},"country":{"id":52,"isocode2":"CO"}},{"id":7536,"name":"Guaranda","state":{"id":741},"country":{"id":52,"isocode2":"CO"}},{"id":7537,"name":"La Union","state":{"id":741},"country":{"id":52,"isocode2":"CO"}},{"id":7538,"name":"Los Palmitos","state":{"id":741},"country":{"id":52,"isocode2":"CO"}},{"id":7539,"name":"Majagual","state":{"id":741},"country":{"id":52,"isocode2":"CO"}},{"id":7540,"name":"Morroa","state":{"id":741},"country":{"id":52,"isocode2":"CO"}},{"id":7541,"name":"Ovejas","state":{"id":741},"country":{"id":52,"isocode2":"CO"}},{"id":7542,"name":"Palmito","state":{"id":741},"country":{"id":52,"isocode2":"CO"}},{"id":7543,"name":"Sampues","state":{"id":741},"country":{"id":52,"isocode2":"CO"}},{"id":7544,"name":"San Benito Abad","state":{"id":741},"country":{"id":52,"isocode2":"CO"}},{"id":7545,"name":"San Juan de Betulia","state":{"id":741},"country":{"id":52,"isocode2":"CO"}},{"id":7546,"name":"San Marcos","state":{"id":741},"country":{"id":52,"isocode2":"CO"}},{"id":7547,"name":"San Onofre","state":{"id":741},"country":{"id":52,"isocode2":"CO"}},{"id":7548,"name":"San Pedro","state":{"id":741},"country":{"id":52,"isocode2":"CO"}},{"id":7549,"name":"Since","state":{"id":741},"country":{"id":52,"isocode2":"CO"}},{"id":7550,"name":"Sincelejo","state":{"id":741},"country":{"id":52,"isocode2":"CO"}},{"id":7551,"name":"Sucre","state":{"id":741},"country":{"id":52,"isocode2":"CO"}},{"id":7552,"name":"Tolu","state":{"id":741},"country":{"id":52,"isocode2":"CO"}},{"id":7553,"name":"Toluviejo","state":{"id":741},"country":{"id":52,"isocode2":"CO"}}]