[{"id":11022,"name":"Friville","state":{"id":1163},"country":{"id":78,"isocode2":"FR"}},{"id":11023,"name":"Liancourt","state":{"id":1163},"country":{"id":78,"isocode2":"FR"}},{"id":11024,"name":"Maizy","state":{"id":1163},"country":{"id":78,"isocode2":"FR"}},{"id":11025,"name":"Oust-Marest","state":{"id":1163},"country":{"id":78,"isocode2":"FR"}},{"id":11026,"name":"Puiseux-le-Hauberger","state":{"id":1163},"country":{"id":78,"isocode2":"FR"}},{"id":11027,"name":"Saint-Crepin-Ibouvillers","state":{"id":1163},"country":{"id":78,"isocode2":"FR"}}]