[{"id":7601,"name":"Acaricuara","state":{"id":744},"country":{"id":52,"isocode2":"CO"}},{"id":7602,"name":"Mitu","state":{"id":744},"country":{"id":52,"isocode2":"CO"}},{"id":7603,"name":"Papunaua","state":{"id":744},"country":{"id":52,"isocode2":"CO"}},{"id":7604,"name":"Taraira","state":{"id":744},"country":{"id":52,"isocode2":"CO"}},{"id":7605,"name":"Villa Fatima","state":{"id":744},"country":{"id":52,"isocode2":"CO"}},{"id":7606,"name":"Yavarate","state":{"id":744},"country":{"id":52,"isocode2":"CO"}}]