[{"id":19248,"name":"Achhalda","state":{"id":1584},"country":{"id":105,"isocode2":"IN"}},{"id":19249,"name":"Achhnera","state":{"id":1584},"country":{"id":105,"isocode2":"IN"}},{"id":19250,"name":"Adari","state":{"id":1584},"country":{"id":105,"isocode2":"IN"}},{"id":19251,"name":"Afzalgarh","state":{"id":1584},"country":{"id":105,"isocode2":"IN"}},{"id":19252,"name":"Agarwal Mandi","state":{"id":1584},"country":{"id":105,"isocode2":"IN"}},{"id":19253,"name":"Agra","state":{"id":1584},"country":{"id":105,"isocode2":"IN"}},{"id":19254,"name":"Agra Cantonment","state":{"id":1584},"country":{"id":105,"isocode2":"IN"}},{"id":19255,"name":"Ahraura","state":{"id":1584},"country":{"id":105,"isocode2":"IN"}},{"id":19256,"name":"Ailum","state":{"id":1584},"country":{"id":105,"isocode2":"IN"}},{"id":19257,"name":"Air Force Area","state":{"id":1584},"country":{"id":105,"isocode2":"IN"}},{"id":19258,"name":"Ajhuwa","state":{"id":1584},"country":{"id":105,"isocode2":"IN"}},{"id":19259,"name":"Akbarpur","state":{"id":1584},"country":{"id":105,"isocode2":"IN"}},{"id":19260,"name":"Alapur","state":{"id":1584},"country":{"id":105,"isocode2":"IN"}},{"id":19261,"name":"Aliganj","state":{"id":1584},"country":{"id":105,"isocode2":"IN"}},{"id":19262,"name":"Aligarh","state":{"id":1584},"country":{"id":105,"isocode2":"IN"}},{"id":19263,"name":"Allahabad","state":{"id":1584},"country":{"id":105,"isocode2":"IN"}},{"id":19264,"name":"Allahabad Cantonment","state":{"id":1584},"country":{"id":105,"isocode2":"IN"}},{"id":19265,"name":"Allahganj","state":{"id":1584},"country":{"id":105,"isocode2":"IN"}},{"id":19266,"name":"Amanpur","state":{"id":1584},"country":{"id":105,"isocode2":"IN"}},{"id":19267,"name":"Ambahta","state":{"id":1584},"country":{"id":105,"isocode2":"IN"}},{"id":19268,"name":"Amethi","state":{"id":1584},"country":{"id":105,"isocode2":"IN"}},{"id":19269,"name":"Amila","state":{"id":1584},"country":{"id":105,"isocode2":"IN"}},{"id":19270,"name":"Amilo","state":{"id":1584},"country":{"id":105,"isocode2":"IN"}},{"id":19271,"name":"Aminagar Sarai","state":{"id":1584},"country":{"id":105,"isocode2":"IN"}},{"id":19272,"name":"Aminagar Urf Bhurbaral","state":{"id":1584},"country":{"id":105,"isocode2":"IN"}},{"id":19273,"name":"Amraudha","state":{"id":1584},"country":{"id":105,"isocode2":"IN"}},{"id":19274,"name":"Amroha","state":{"id":1584},"country":{"id":105,"isocode2":"IN"}},{"id":19275,"name":"Anandnagar","state":{"id":1584},"country":{"id":105,"isocode2":"IN"}},{"id":19276,"name":"Anpara","state":{"id":1584},"country":{"id":105,"isocode2":"IN"}},{"id":19277,"name":"Antu","state":{"id":1584},"country":{"id":105,"isocode2":"IN"}},{"id":19278,"name":"Anupshahr","state":{"id":1584},"country":{"id":105,"isocode2":"IN"}},{"id":19279,"name":"Aonla","state":{"id":1584},"country":{"id":105,"isocode2":"IN"}},{"id":19280,"name":"Armapur Estate","state":{"id":1584},"country":{"id":105,"isocode2":"IN"}},{"id":19281,"name":"Ashokpuram","state":{"id":1584},"country":{"id":105,"isocode2":"IN"}},{"id":19282,"name":"Ashrafpur Kichhauchha","state":{"id":1584},"country":{"id":105,"isocode2":"IN"}},{"id":19283,"name":"Atarra","state":{"id":1584},"country":{"id":105,"isocode2":"IN"}},{"id":19284,"name":"Atasu","state":{"id":1584},"country":{"id":105,"isocode2":"IN"}},{"id":19285,"name":"Atrauli","state":{"id":1584},"country":{"id":105,"isocode2":"IN"}},{"id":19286,"name":"Atraulia","state":{"id":1584},"country":{"id":105,"isocode2":"IN"}},{"id":19287,"name":"Auraiya","state":{"id":1584},"country":{"id":105,"isocode2":"IN"}},{"id":19288,"name":"Aurangabad","state":{"id":1584},"country":{"id":105,"isocode2":"IN"}},{"id":19289,"name":"Aurangabad Bangar","state":{"id":1584},"country":{"id":105,"isocode2":"IN"}},{"id":19290,"name":"Auras","state":{"id":1584},"country":{"id":105,"isocode2":"IN"}},{"id":19291,"name":"Awagarh","state":{"id":1584},"country":{"id":105,"isocode2":"IN"}},{"id":19292,"name":"Ayodhya","state":{"id":1584},"country":{"id":105,"isocode2":"IN"}},{"id":19293,"name":"Azamgarh","state":{"id":1584},"country":{"id":105,"isocode2":"IN"}},{"id":19294,"name":"Azizpur","state":{"id":1584},"country":{"id":105,"isocode2":"IN"}},{"id":19295,"name":"Azmatgarh","state":{"id":1584},"country":{"id":105,"isocode2":"IN"}},{"id":19296,"name":"Babarpur Ajitmal","state":{"id":1584},"country":{"id":105,"isocode2":"IN"}},{"id":19297,"name":"Baberu","state":{"id":1584},"country":{"id":105,"isocode2":"IN"}},{"id":19298,"name":"Babina","state":{"id":1584},"country":{"id":105,"isocode2":"IN"}},{"id":19299,"name":"Babrala","state":{"id":1584},"country":{"id":105,"isocode2":"IN"}},{"id":19300,"name":"Babugarh","state":{"id":1584},"country":{"id":105,"isocode2":"IN"}},{"id":19301,"name":"Bachhiowan","state":{"id":1584},"country":{"id":105,"isocode2":"IN"}},{"id":19302,"name":"Bachhraon","state":{"id":1584},"country":{"id":105,"isocode2":"IN"}},{"id":19303,"name":"Bad","state":{"id":1584},"country":{"id":105,"isocode2":"IN"}},{"id":19304,"name":"Badaun","state":{"id":1584},"country":{"id":105,"isocode2":"IN"}},{"id":19305,"name":"Baghpat","state":{"id":1584},"country":{"id":105,"isocode2":"IN"}},{"id":19306,"name":"Bah","state":{"id":1584},"country":{"id":105,"isocode2":"IN"}},{"id":19307,"name":"Bahadurganj","state":{"id":1584},"country":{"id":105,"isocode2":"IN"}},{"id":19308,"name":"Baheri","state":{"id":1584},"country":{"id":105,"isocode2":"IN"}},{"id":19309,"name":"Bahjoi","state":{"id":1584},"country":{"id":105,"isocode2":"IN"}},{"id":19310,"name":"Bahraich","state":{"id":1584},"country":{"id":105,"isocode2":"IN"}},{"id":19311,"name":"Bahsuma","state":{"id":1584},"country":{"id":105,"isocode2":"IN"}},{"id":19312,"name":"Bahua","state":{"id":1584},"country":{"id":105,"isocode2":"IN"}},{"id":19313,"name":"Bajna","state":{"id":1584},"country":{"id":105,"isocode2":"IN"}},{"id":19314,"name":"Bakewar","state":{"id":1584},"country":{"id":105,"isocode2":"IN"}},{"id":19315,"name":"Bakiabad","state":{"id":1584},"country":{"id":105,"isocode2":"IN"}},{"id":19316,"name":"Baldeo","state":{"id":1584},"country":{"id":105,"isocode2":"IN"}},{"id":19317,"name":"Ballia","state":{"id":1584},"country":{"id":105,"isocode2":"IN"}},{"id":19318,"name":"Balrampur","state":{"id":1584},"country":{"id":105,"isocode2":"IN"}},{"id":19319,"name":"Banat","state":{"id":1584},"country":{"id":105,"isocode2":"IN"}},{"id":19320,"name":"Banda","state":{"id":1584},"country":{"id":105,"isocode2":"IN"}},{"id":19321,"name":"Bangarmau","state":{"id":1584},"country":{"id":105,"isocode2":"IN"}},{"id":19322,"name":"Banki","state":{"id":1584},"country":{"id":105,"isocode2":"IN"}},{"id":19323,"name":"Bansdih","state":{"id":1584},"country":{"id":105,"isocode2":"IN"}},{"id":19324,"name":"Bansgaon","state":{"id":1584},"country":{"id":105,"isocode2":"IN"}},{"id":19325,"name":"Bansi","state":{"id":1584},"country":{"id":105,"isocode2":"IN"}},{"id":19326,"name":"Barabanki","state":{"id":1584},"country":{"id":105,"isocode2":"IN"}},{"id":19327,"name":"Baragaon","state":{"id":1584},"country":{"id":105,"isocode2":"IN"}},{"id":19328,"name":"Baraut","state":{"id":1584},"country":{"id":105,"isocode2":"IN"}},{"id":19329,"name":"Bareilly","state":{"id":1584},"country":{"id":105,"isocode2":"IN"}},{"id":19330,"name":"Bareilly Cantonment","state":{"id":1584},"country":{"id":105,"isocode2":"IN"}},{"id":19331,"name":"Barhalganj","state":{"id":1584},"country":{"id":105,"isocode2":"IN"}},{"id":19332,"name":"Barhani","state":{"id":1584},"country":{"id":105,"isocode2":"IN"}},{"id":19333,"name":"Barhapur","state":{"id":1584},"country":{"id":105,"isocode2":"IN"}},{"id":19334,"name":"Barkhera","state":{"id":1584},"country":{"id":105,"isocode2":"IN"}},{"id":19335,"name":"Barsana","state":{"id":1584},"country":{"id":105,"isocode2":"IN"}},{"id":19336,"name":"Barva Sagar","state":{"id":1584},"country":{"id":105,"isocode2":"IN"}},{"id":19337,"name":"Barwar","state":{"id":1584},"country":{"id":105,"isocode2":"IN"}},{"id":19338,"name":"Basti","state":{"id":1584},"country":{"id":105,"isocode2":"IN"}},{"id":19339,"name":"Begumabad Budhana","state":{"id":1584},"country":{"id":105,"isocode2":"IN"}},{"id":19340,"name":"Behat","state":{"id":1584},"country":{"id":105,"isocode2":"IN"}},{"id":19341,"name":"Behta Hajipur","state":{"id":1584},"country":{"id":105,"isocode2":"IN"}},{"id":19342,"name":"Bela","state":{"id":1584},"country":{"id":105,"isocode2":"IN"}},{"id":19343,"name":"Belthara","state":{"id":1584},"country":{"id":105,"isocode2":"IN"}},{"id":19344,"name":"Beniganj","state":{"id":1584},"country":{"id":105,"isocode2":"IN"}},{"id":19345,"name":"Beswan","state":{"id":1584},"country":{"id":105,"isocode2":"IN"}},{"id":19346,"name":"Bewar","state":{"id":1584},"country":{"id":105,"isocode2":"IN"}},{"id":19347,"name":"Bhadarsa","state":{"id":1584},"country":{"id":105,"isocode2":"IN"}},{"id":19348,"name":"Bhadohi","state":{"id":1584},"country":{"id":105,"isocode2":"IN"}},{"id":19349,"name":"Bhagwantnagar","state":{"id":1584},"country":{"id":105,"isocode2":"IN"}},{"id":19350,"name":"Bharatganj","state":{"id":1584},"country":{"id":105,"isocode2":"IN"}},{"id":19351,"name":"Bhargain","state":{"id":1584},"country":{"id":105,"isocode2":"IN"}},{"id":19352,"name":"Bharthana","state":{"id":1584},"country":{"id":105,"isocode2":"IN"}},{"id":19353,"name":"Bharuhana","state":{"id":1584},"country":{"id":105,"isocode2":"IN"}},{"id":19354,"name":"Bharwari","state":{"id":1584},"country":{"id":105,"isocode2":"IN"}},{"id":19355,"name":"Bhatni Bazar","state":{"id":1584},"country":{"id":105,"isocode2":"IN"}},{"id":19356,"name":"Bhatpar Rani","state":{"id":1584},"country":{"id":105,"isocode2":"IN"}},{"id":19357,"name":"Bhawan Bahadurnagar","state":{"id":1584},"country":{"id":105,"isocode2":"IN"}},{"id":19358,"name":"Bhinga","state":{"id":1584},"country":{"id":105,"isocode2":"IN"}},{"id":19359,"name":"Bhojpur Dharampur","state":{"id":1584},"country":{"id":105,"isocode2":"IN"}},{"id":19360,"name":"Bhokarhedi","state":{"id":1584},"country":{"id":105,"isocode2":"IN"}},{"id":19361,"name":"Bhongaon","state":{"id":1584},"country":{"id":105,"isocode2":"IN"}},{"id":19362,"name":"Bhulepur","state":{"id":1584},"country":{"id":105,"isocode2":"IN"}},{"id":19363,"name":"Bidhuna","state":{"id":1584},"country":{"id":105,"isocode2":"IN"}},{"id":19364,"name":"Bighapur","state":{"id":1584},"country":{"id":105,"isocode2":"IN"}},{"id":19365,"name":"Bijnor","state":{"id":1584},"country":{"id":105,"isocode2":"IN"}},{"id":19366,"name":"Bijpur","state":{"id":1584},"country":{"id":105,"isocode2":"IN"}},{"id":19367,"name":"Bikapur","state":{"id":1584},"country":{"id":105,"isocode2":"IN"}},{"id":19368,"name":"Bilari","state":{"id":1584},"country":{"id":105,"isocode2":"IN"}},{"id":19369,"name":"Bilaspur","state":{"id":1584},"country":{"id":105,"isocode2":"IN"}},{"id":19370,"name":"Bilgram","state":{"id":1584},"country":{"id":105,"isocode2":"IN"}},{"id":19371,"name":"Bilhaur","state":{"id":1584},"country":{"id":105,"isocode2":"IN"}},{"id":19372,"name":"Bilram","state":{"id":1584},"country":{"id":105,"isocode2":"IN"}},{"id":19373,"name":"Bilrayaganj","state":{"id":1584},"country":{"id":105,"isocode2":"IN"}},{"id":19374,"name":"Bilsanda","state":{"id":1584},"country":{"id":105,"isocode2":"IN"}},{"id":19375,"name":"Bilsi","state":{"id":1584},"country":{"id":105,"isocode2":"IN"}},{"id":19376,"name":"Bindki","state":{"id":1584},"country":{"id":105,"isocode2":"IN"}},{"id":19377,"name":"Bisalpur","state":{"id":1584},"country":{"id":105,"isocode2":"IN"}},{"id":19378,"name":"Bisanda Buzurg","state":{"id":1584},"country":{"id":105,"isocode2":"IN"}},{"id":19379,"name":"Bisauli","state":{"id":1584},"country":{"id":105,"isocode2":"IN"}},{"id":19380,"name":"Bisharatganj","state":{"id":1584},"country":{"id":105,"isocode2":"IN"}},{"id":19381,"name":"Bisokhar","state":{"id":1584},"country":{"id":105,"isocode2":"IN"}},{"id":19382,"name":"Biswan","state":{"id":1584},"country":{"id":105,"isocode2":"IN"}},{"id":19383,"name":"Bithur","state":{"id":1584},"country":{"id":105,"isocode2":"IN"}},{"id":19384,"name":"Budaun","state":{"id":1584},"country":{"id":105,"isocode2":"IN"}},{"id":19385,"name":"Bugrasi","state":{"id":1584},"country":{"id":105,"isocode2":"IN"}},{"id":19386,"name":"Bulandshahar","state":{"id":1584},"country":{"id":105,"isocode2":"IN"}},{"id":19387,"name":"Burhana","state":{"id":1584},"country":{"id":105,"isocode2":"IN"}},{"id":19388,"name":"Chail","state":{"id":1584},"country":{"id":105,"isocode2":"IN"}},{"id":19389,"name":"Chak Imam Ali","state":{"id":1584},"country":{"id":105,"isocode2":"IN"}},{"id":19390,"name":"Chakeri","state":{"id":1584},"country":{"id":105,"isocode2":"IN"}},{"id":19391,"name":"Chakia","state":{"id":1584},"country":{"id":105,"isocode2":"IN"}},{"id":19392,"name":"Chandauli","state":{"id":1584},"country":{"id":105,"isocode2":"IN"}},{"id":19393,"name":"Chandausi","state":{"id":1584},"country":{"id":105,"isocode2":"IN"}},{"id":19394,"name":"Chandpur","state":{"id":1584},"country":{"id":105,"isocode2":"IN"}},{"id":19395,"name":"Charkhari","state":{"id":1584},"country":{"id":105,"isocode2":"IN"}},{"id":19396,"name":"Charthawal","state":{"id":1584},"country":{"id":105,"isocode2":"IN"}},{"id":19397,"name":"Chaumuhan","state":{"id":1584},"country":{"id":105,"isocode2":"IN"}},{"id":19398,"name":"Chhaprauli","state":{"id":1584},"country":{"id":105,"isocode2":"IN"}},{"id":19399,"name":"Chhara Rafatpur","state":{"id":1584},"country":{"id":105,"isocode2":"IN"}},{"id":19400,"name":"Chharprauli","state":{"id":1584},"country":{"id":105,"isocode2":"IN"}},{"id":19401,"name":"Chhata","state":{"id":1584},"country":{"id":105,"isocode2":"IN"}},{"id":19402,"name":"Chhatari","state":{"id":1584},"country":{"id":105,"isocode2":"IN"}},{"id":19403,"name":"Chhibramau","state":{"id":1584},"country":{"id":105,"isocode2":"IN"}},{"id":19404,"name":"Chhutmalpur","state":{"id":1584},"country":{"id":105,"isocode2":"IN"}},{"id":19405,"name":"Chilkana Sultanpur","state":{"id":1584},"country":{"id":105,"isocode2":"IN"}},{"id":19406,"name":"Chirgaon","state":{"id":1584},"country":{"id":105,"isocode2":"IN"}},{"id":19407,"name":"Chit Baragaon","state":{"id":1584},"country":{"id":105,"isocode2":"IN"}},{"id":19408,"name":"Chitrakut Dham","state":{"id":1584},"country":{"id":105,"isocode2":"IN"}},{"id":19409,"name":"Chopan","state":{"id":1584},"country":{"id":105,"isocode2":"IN"}},{"id":19410,"name":"Choubepur Kalan","state":{"id":1584},"country":{"id":105,"isocode2":"IN"}},{"id":19411,"name":"Chunar","state":{"id":1584},"country":{"id":105,"isocode2":"IN"}},{"id":19412,"name":"Churk Ghurma","state":{"id":1584},"country":{"id":105,"isocode2":"IN"}},{"id":19413,"name":"Colonelganj","state":{"id":1584},"country":{"id":105,"isocode2":"IN"}},{"id":19414,"name":"Dadri","state":{"id":1584},"country":{"id":105,"isocode2":"IN"}},{"id":19415,"name":"Dalmau","state":{"id":1584},"country":{"id":105,"isocode2":"IN"}},{"id":19416,"name":"Dankaur","state":{"id":1584},"country":{"id":105,"isocode2":"IN"}},{"id":19417,"name":"Dariyabad","state":{"id":1584},"country":{"id":105,"isocode2":"IN"}},{"id":19418,"name":"Dasna","state":{"id":1584},"country":{"id":105,"isocode2":"IN"}},{"id":19419,"name":"Dataganj","state":{"id":1584},"country":{"id":105,"isocode2":"IN"}},{"id":19420,"name":"Daurala","state":{"id":1584},"country":{"id":105,"isocode2":"IN"}},{"id":19421,"name":"Dayal Bagh","state":{"id":1584},"country":{"id":105,"isocode2":"IN"}},{"id":19422,"name":"Deoband","state":{"id":1584},"country":{"id":105,"isocode2":"IN"}},{"id":19423,"name":"Deoranian","state":{"id":1584},"country":{"id":105,"isocode2":"IN"}},{"id":19424,"name":"Deoria","state":{"id":1584},"country":{"id":105,"isocode2":"IN"}},{"id":19425,"name":"Dewa","state":{"id":1584},"country":{"id":105,"isocode2":"IN"}},{"id":19426,"name":"Dhampur","state":{"id":1584},"country":{"id":105,"isocode2":"IN"}},{"id":19427,"name":"Dhanauha","state":{"id":1584},"country":{"id":105,"isocode2":"IN"}},{"id":19428,"name":"Dhanauli","state":{"id":1584},"country":{"id":105,"isocode2":"IN"}},{"id":19429,"name":"Dhanaura","state":{"id":1584},"country":{"id":105,"isocode2":"IN"}},{"id":19430,"name":"Dharoti Khurd","state":{"id":1584},"country":{"id":105,"isocode2":"IN"}},{"id":19431,"name":"Dhauratanda","state":{"id":1584},"country":{"id":105,"isocode2":"IN"}},{"id":19432,"name":"Dhaurhra","state":{"id":1584},"country":{"id":105,"isocode2":"IN"}},{"id":19433,"name":"Dibai","state":{"id":1584},"country":{"id":105,"isocode2":"IN"}},{"id":19434,"name":"Dibiyapur","state":{"id":1584},"country":{"id":105,"isocode2":"IN"}},{"id":19435,"name":"Dildarnagar Fatehpur","state":{"id":1584},"country":{"id":105,"isocode2":"IN"}},{"id":19436,"name":"Do Ghat","state":{"id":1584},"country":{"id":105,"isocode2":"IN"}},{"id":19437,"name":"Dohrighat","state":{"id":1584},"country":{"id":105,"isocode2":"IN"}},{"id":19438,"name":"Dostpur","state":{"id":1584},"country":{"id":105,"isocode2":"IN"}},{"id":19439,"name":"Dudhinagar","state":{"id":1584},"country":{"id":105,"isocode2":"IN"}},{"id":19440,"name":"Dulhipur","state":{"id":1584},"country":{"id":105,"isocode2":"IN"}},{"id":19441,"name":"Dundwaraganj","state":{"id":1584},"country":{"id":105,"isocode2":"IN"}},{"id":19442,"name":"Ekdil","state":{"id":1584},"country":{"id":105,"isocode2":"IN"}},{"id":19443,"name":"Erich","state":{"id":1584},"country":{"id":105,"isocode2":"IN"}},{"id":19444,"name":"Etah","state":{"id":1584},"country":{"id":105,"isocode2":"IN"}},{"id":19445,"name":"Etawah","state":{"id":1584},"country":{"id":105,"isocode2":"IN"}},{"id":19446,"name":"Faizabad","state":{"id":1584},"country":{"id":105,"isocode2":"IN"}},{"id":19447,"name":"Faizabad Cantonment","state":{"id":1584},"country":{"id":105,"isocode2":"IN"}},{"id":19448,"name":"Faizganj","state":{"id":1584},"country":{"id":105,"isocode2":"IN"}},{"id":19449,"name":"Farah","state":{"id":1584},"country":{"id":105,"isocode2":"IN"}},{"id":19450,"name":"Faridnagar","state":{"id":1584},"country":{"id":105,"isocode2":"IN"}},{"id":19451,"name":"Faridpur","state":{"id":1584},"country":{"id":105,"isocode2":"IN"}},{"id":19452,"name":"Faridpur Cantonment","state":{"id":1584},"country":{"id":105,"isocode2":"IN"}},{"id":19453,"name":"Fariha","state":{"id":1584},"country":{"id":105,"isocode2":"IN"}},{"id":19454,"name":"Farrukhabad","state":{"id":1584},"country":{"id":105,"isocode2":"IN"}},{"id":19455,"name":"Fatehabad","state":{"id":1584},"country":{"id":105,"isocode2":"IN"}},{"id":19456,"name":"Fatehganj Pashchimi","state":{"id":1584},"country":{"id":105,"isocode2":"IN"}},{"id":19457,"name":"Fatehganj Purvi","state":{"id":1584},"country":{"id":105,"isocode2":"IN"}},{"id":19458,"name":"Fatehgarh","state":{"id":1584},"country":{"id":105,"isocode2":"IN"}},{"id":19459,"name":"Fatehpur","state":{"id":1584},"country":{"id":105,"isocode2":"IN"}},{"id":19460,"name":"Fatehpur Chaurasi","state":{"id":1584},"country":{"id":105,"isocode2":"IN"}},{"id":19461,"name":"Fatehpur Sikri","state":{"id":1584},"country":{"id":105,"isocode2":"IN"}},{"id":19462,"name":"Firozabad","state":{"id":1584},"country":{"id":105,"isocode2":"IN"}},{"id":19463,"name":"Gajraula","state":{"id":1584},"country":{"id":105,"isocode2":"IN"}},{"id":19464,"name":"Ganga Ghat","state":{"id":1584},"country":{"id":105,"isocode2":"IN"}},{"id":19465,"name":"Gangapur","state":{"id":1584},"country":{"id":105,"isocode2":"IN"}},{"id":19466,"name":"Gangoh","state":{"id":1584},"country":{"id":105,"isocode2":"IN"}},{"id":19467,"name":"Ganj Muradabad","state":{"id":1584},"country":{"id":105,"isocode2":"IN"}},{"id":19468,"name":"Garautha","state":{"id":1584},"country":{"id":105,"isocode2":"IN"}},{"id":19469,"name":"Garhi Pukhta","state":{"id":1584},"country":{"id":105,"isocode2":"IN"}},{"id":19470,"name":"Garhmukteshwar","state":{"id":1584},"country":{"id":105,"isocode2":"IN"}},{"id":19471,"name":"Gaura Barahaj","state":{"id":1584},"country":{"id":105,"isocode2":"IN"}},{"id":19472,"name":"Gauri Bazar","state":{"id":1584},"country":{"id":105,"isocode2":"IN"}},{"id":19473,"name":"Gausganj","state":{"id":1584},"country":{"id":105,"isocode2":"IN"}},{"id":19474,"name":"Gawan","state":{"id":1584},"country":{"id":105,"isocode2":"IN"}},{"id":19475,"name":"Ghatampur","state":{"id":1584},"country":{"id":105,"isocode2":"IN"}},{"id":19476,"name":"Ghaziabad","state":{"id":1584},"country":{"id":105,"isocode2":"IN"}},{"id":19477,"name":"Ghazipur","state":{"id":1584},"country":{"id":105,"isocode2":"IN"}},{"id":19478,"name":"Ghiror","state":{"id":1584},"country":{"id":105,"isocode2":"IN"}},{"id":19479,"name":"Ghorawal","state":{"id":1584},"country":{"id":105,"isocode2":"IN"}},{"id":19480,"name":"Ghosi","state":{"id":1584},"country":{"id":105,"isocode2":"IN"}},{"id":19481,"name":"Ghosia Bazar","state":{"id":1584},"country":{"id":105,"isocode2":"IN"}},{"id":19482,"name":"Ghughuli","state":{"id":1584},"country":{"id":105,"isocode2":"IN"}},{"id":19483,"name":"Gohand","state":{"id":1584},"country":{"id":105,"isocode2":"IN"}},{"id":19484,"name":"Gokul","state":{"id":1584},"country":{"id":105,"isocode2":"IN"}},{"id":19485,"name":"Gola Bazar","state":{"id":1584},"country":{"id":105,"isocode2":"IN"}},{"id":19486,"name":"Gola Gokarannath","state":{"id":1584},"country":{"id":105,"isocode2":"IN"}},{"id":19487,"name":"Gonda","state":{"id":1584},"country":{"id":105,"isocode2":"IN"}},{"id":19488,"name":"Gopamau","state":{"id":1584},"country":{"id":105,"isocode2":"IN"}},{"id":19489,"name":"Gopiganj","state":{"id":1584},"country":{"id":105,"isocode2":"IN"}},{"id":19490,"name":"Gorakhpur","state":{"id":1584},"country":{"id":105,"isocode2":"IN"}},{"id":19491,"name":"Gosainganj","state":{"id":1584},"country":{"id":105,"isocode2":"IN"}},{"id":19492,"name":"Govardhan","state":{"id":1584},"country":{"id":105,"isocode2":"IN"}},{"id":19493,"name":"Greater Noida","state":{"id":1584},"country":{"id":105,"isocode2":"IN"}},{"id":19494,"name":"Gulaothi","state":{"id":1584},"country":{"id":105,"isocode2":"IN"}},{"id":19495,"name":"Gulariya","state":{"id":1584},"country":{"id":105,"isocode2":"IN"}},{"id":19496,"name":"Gulariya Bhindara","state":{"id":1584},"country":{"id":105,"isocode2":"IN"}},{"id":19497,"name":"Gunnaur","state":{"id":1584},"country":{"id":105,"isocode2":"IN"}},{"id":19498,"name":"Gursahaiganj","state":{"id":1584},"country":{"id":105,"isocode2":"IN"}},{"id":19499,"name":"Gursarai","state":{"id":1584},"country":{"id":105,"isocode2":"IN"}},{"id":19500,"name":"Gyanpur","state":{"id":1584},"country":{"id":105,"isocode2":"IN"}},{"id":19501,"name":"Hafizpur","state":{"id":1584},"country":{"id":105,"isocode2":"IN"}},{"id":19502,"name":"Haidergarh","state":{"id":1584},"country":{"id":105,"isocode2":"IN"}},{"id":19503,"name":"Haldaur","state":{"id":1584},"country":{"id":105,"isocode2":"IN"}},{"id":19504,"name":"Hamirpur","state":{"id":1584},"country":{"id":105,"isocode2":"IN"}},{"id":19505,"name":"Handia","state":{"id":1584},"country":{"id":105,"isocode2":"IN"}},{"id":19506,"name":"Hapur","state":{"id":1584},"country":{"id":105,"isocode2":"IN"}},{"id":19507,"name":"Hardoi","state":{"id":1584},"country":{"id":105,"isocode2":"IN"}},{"id":19508,"name":"Harduaganj","state":{"id":1584},"country":{"id":105,"isocode2":"IN"}},{"id":19509,"name":"Hargaon","state":{"id":1584},"country":{"id":105,"isocode2":"IN"}},{"id":19510,"name":"Hariharpur","state":{"id":1584},"country":{"id":105,"isocode2":"IN"}},{"id":19511,"name":"Harraiya","state":{"id":1584},"country":{"id":105,"isocode2":"IN"}},{"id":19512,"name":"Hasanpur","state":{"id":1584},"country":{"id":105,"isocode2":"IN"}},{"id":19513,"name":"Hasayan","state":{"id":1584},"country":{"id":105,"isocode2":"IN"}},{"id":19514,"name":"Hastinapur","state":{"id":1584},"country":{"id":105,"isocode2":"IN"}},{"id":19515,"name":"Hata","state":{"id":1584},"country":{"id":105,"isocode2":"IN"}},{"id":19516,"name":"Hathras","state":{"id":1584},"country":{"id":105,"isocode2":"IN"}},{"id":19517,"name":"Hyderabad","state":{"id":1584},"country":{"id":105,"isocode2":"IN"}},{"id":19518,"name":"Ibrahimpur","state":{"id":1584},"country":{"id":105,"isocode2":"IN"}},{"id":19519,"name":"Iglas","state":{"id":1584},"country":{"id":105,"isocode2":"IN"}},{"id":19520,"name":"Ikauna","state":{"id":1584},"country":{"id":105,"isocode2":"IN"}},{"id":19521,"name":"Iltifatganj Bazar","state":{"id":1584},"country":{"id":105,"isocode2":"IN"}},{"id":19522,"name":"Indian Telephone Industry Mank","state":{"id":1584},"country":{"id":105,"isocode2":"IN"}},{"id":19523,"name":"Islamnagar","state":{"id":1584},"country":{"id":105,"isocode2":"IN"}},{"id":19524,"name":"Itaunja","state":{"id":1584},"country":{"id":105,"isocode2":"IN"}},{"id":19525,"name":"Itimadpur","state":{"id":1584},"country":{"id":105,"isocode2":"IN"}},{"id":19526,"name":"Jagner","state":{"id":1584},"country":{"id":105,"isocode2":"IN"}},{"id":19527,"name":"Jahanabad","state":{"id":1584},"country":{"id":105,"isocode2":"IN"}},{"id":19528,"name":"Jahangirabad","state":{"id":1584},"country":{"id":105,"isocode2":"IN"}},{"id":19529,"name":"Jahangirpur","state":{"id":1584},"country":{"id":105,"isocode2":"IN"}},{"id":19530,"name":"Jais","state":{"id":1584},"country":{"id":105,"isocode2":"IN"}},{"id":19531,"name":"Jaithara","state":{"id":1584},"country":{"id":105,"isocode2":"IN"}},{"id":19532,"name":"Jalalabad","state":{"id":1584},"country":{"id":105,"isocode2":"IN"}},{"id":19533,"name":"Jalali","state":{"id":1584},"country":{"id":105,"isocode2":"IN"}},{"id":19534,"name":"Jalalpur","state":{"id":1584},"country":{"id":105,"isocode2":"IN"}},{"id":19535,"name":"Jalaun","state":{"id":1584},"country":{"id":105,"isocode2":"IN"}},{"id":19536,"name":"Jalesar","state":{"id":1584},"country":{"id":105,"isocode2":"IN"}},{"id":19537,"name":"Jamshila","state":{"id":1584},"country":{"id":105,"isocode2":"IN"}},{"id":19538,"name":"Jangipur","state":{"id":1584},"country":{"id":105,"isocode2":"IN"}},{"id":19539,"name":"Jansath","state":{"id":1584},"country":{"id":105,"isocode2":"IN"}},{"id":19540,"name":"Jarwal","state":{"id":1584},"country":{"id":105,"isocode2":"IN"}},{"id":19541,"name":"Jasrana","state":{"id":1584},"country":{"id":105,"isocode2":"IN"}},{"id":19542,"name":"Jaswantnagar","state":{"id":1584},"country":{"id":105,"isocode2":"IN"}},{"id":19543,"name":"Jatari","state":{"id":1584},"country":{"id":105,"isocode2":"IN"}},{"id":19544,"name":"Jaunpur","state":{"id":1584},"country":{"id":105,"isocode2":"IN"}},{"id":19545,"name":"Jewar","state":{"id":1584},"country":{"id":105,"isocode2":"IN"}},{"id":19546,"name":"Jhalu","state":{"id":1584},"country":{"id":105,"isocode2":"IN"}},{"id":19547,"name":"Jhansi","state":{"id":1584},"country":{"id":105,"isocode2":"IN"}},{"id":19548,"name":"Jhansi Cantonment","state":{"id":1584},"country":{"id":105,"isocode2":"IN"}},{"id":19549,"name":"Jhansi Railway Settlement","state":{"id":1584},"country":{"id":105,"isocode2":"IN"}},{"id":19550,"name":"Jhinjhak","state":{"id":1584},"country":{"id":105,"isocode2":"IN"}},{"id":19551,"name":"Jhinjhana","state":{"id":1584},"country":{"id":105,"isocode2":"IN"}},{"id":19552,"name":"Jhusi","state":{"id":1584},"country":{"id":105,"isocode2":"IN"}},{"id":19553,"name":"Jhusi Kohna","state":{"id":1584},"country":{"id":105,"isocode2":"IN"}},{"id":19554,"name":"Jiyanpur","state":{"id":1584},"country":{"id":105,"isocode2":"IN"}},{"id":19555,"name":"Joya","state":{"id":1584},"country":{"id":105,"isocode2":"IN"}},{"id":19556,"name":"Jyoti Khuria","state":{"id":1584},"country":{"id":105,"isocode2":"IN"}},{"id":19557,"name":"Jyotiba Phule Nagar","state":{"id":1584},"country":{"id":105,"isocode2":"IN"}},{"id":19558,"name":"Kabrai","state":{"id":1584},"country":{"id":105,"isocode2":"IN"}},{"id":19559,"name":"Kachhauna Patseni","state":{"id":1584},"country":{"id":105,"isocode2":"IN"}},{"id":19560,"name":"Kachhla","state":{"id":1584},"country":{"id":105,"isocode2":"IN"}},{"id":19561,"name":"Kachhwa","state":{"id":1584},"country":{"id":105,"isocode2":"IN"}},{"id":19562,"name":"Kadaura","state":{"id":1584},"country":{"id":105,"isocode2":"IN"}},{"id":19563,"name":"Kadipur","state":{"id":1584},"country":{"id":105,"isocode2":"IN"}},{"id":19564,"name":"Kailashpur","state":{"id":1584},"country":{"id":105,"isocode2":"IN"}},{"id":19565,"name":"Kaimganj","state":{"id":1584},"country":{"id":105,"isocode2":"IN"}},{"id":19566,"name":"Kairana","state":{"id":1584},"country":{"id":105,"isocode2":"IN"}},{"id":19567,"name":"Kakgaina","state":{"id":1584},"country":{"id":105,"isocode2":"IN"}},{"id":19568,"name":"Kakod","state":{"id":1584},"country":{"id":105,"isocode2":"IN"}},{"id":19569,"name":"Kakori","state":{"id":1584},"country":{"id":105,"isocode2":"IN"}},{"id":19570,"name":"Kakrala","state":{"id":1584},"country":{"id":105,"isocode2":"IN"}},{"id":19571,"name":"Kalinagar","state":{"id":1584},"country":{"id":105,"isocode2":"IN"}},{"id":19572,"name":"Kalpi","state":{"id":1584},"country":{"id":105,"isocode2":"IN"}},{"id":19573,"name":"Kamalganj","state":{"id":1584},"country":{"id":105,"isocode2":"IN"}},{"id":19574,"name":"Kampil","state":{"id":1584},"country":{"id":105,"isocode2":"IN"}},{"id":19575,"name":"Kandhla","state":{"id":1584},"country":{"id":105,"isocode2":"IN"}},{"id":19576,"name":"Kandwa","state":{"id":1584},"country":{"id":105,"isocode2":"IN"}},{"id":19577,"name":"Kannauj","state":{"id":1584},"country":{"id":105,"isocode2":"IN"}},{"id":19578,"name":"Kanpur","state":{"id":1584},"country":{"id":105,"isocode2":"IN"}},{"id":19579,"name":"Kant","state":{"id":1584},"country":{"id":105,"isocode2":"IN"}},{"id":19580,"name":"Kanth","state":{"id":1584},"country":{"id":105,"isocode2":"IN"}},{"id":19581,"name":"Kaptanganj","state":{"id":1584},"country":{"id":105,"isocode2":"IN"}},{"id":19582,"name":"Karaon","state":{"id":1584},"country":{"id":105,"isocode2":"IN"}},{"id":19583,"name":"Karari","state":{"id":1584},"country":{"id":105,"isocode2":"IN"}},{"id":19584,"name":"Karhal","state":{"id":1584},"country":{"id":105,"isocode2":"IN"}},{"id":19585,"name":"Karnawal","state":{"id":1584},"country":{"id":105,"isocode2":"IN"}},{"id":19586,"name":"Kasganj","state":{"id":1584},"country":{"id":105,"isocode2":"IN"}},{"id":19587,"name":"Katariya","state":{"id":1584},"country":{"id":105,"isocode2":"IN"}},{"id":19588,"name":"Katghar Lalganj","state":{"id":1584},"country":{"id":105,"isocode2":"IN"}},{"id":19589,"name":"Kathera","state":{"id":1584},"country":{"id":105,"isocode2":"IN"}},{"id":19590,"name":"Katra","state":{"id":1584},"country":{"id":105,"isocode2":"IN"}},{"id":19591,"name":"Katra Medniganj","state":{"id":1584},"country":{"id":105,"isocode2":"IN"}},{"id":19592,"name":"Kauriaganj","state":{"id":1584},"country":{"id":105,"isocode2":"IN"}},{"id":19593,"name":"Kemri","state":{"id":1584},"country":{"id":105,"isocode2":"IN"}},{"id":19594,"name":"Kerakat","state":{"id":1584},"country":{"id":105,"isocode2":"IN"}},{"id":19595,"name":"Khadda","state":{"id":1584},"country":{"id":105,"isocode2":"IN"}},{"id":19596,"name":"Khaga","state":{"id":1584},"country":{"id":105,"isocode2":"IN"}},{"id":19597,"name":"Khailar","state":{"id":1584},"country":{"id":105,"isocode2":"IN"}},{"id":19598,"name":"Khair","state":{"id":1584},"country":{"id":105,"isocode2":"IN"}},{"id":19599,"name":"Khairabad","state":{"id":1584},"country":{"id":105,"isocode2":"IN"}},{"id":19600,"name":"Khairagarh","state":{"id":1584},"country":{"id":105,"isocode2":"IN"}},{"id":19601,"name":"Khalilabad","state":{"id":1584},"country":{"id":105,"isocode2":"IN"}},{"id":19602,"name":"Khamaria","state":{"id":1584},"country":{"id":105,"isocode2":"IN"}},{"id":19603,"name":"Khanpur","state":{"id":1584},"country":{"id":105,"isocode2":"IN"}},{"id":19604,"name":"Kharela","state":{"id":1584},"country":{"id":105,"isocode2":"IN"}},{"id":19605,"name":"Khargupur","state":{"id":1584},"country":{"id":105,"isocode2":"IN"}},{"id":19606,"name":"Khariya","state":{"id":1584},"country":{"id":105,"isocode2":"IN"}},{"id":19607,"name":"Kharkhoda","state":{"id":1584},"country":{"id":105,"isocode2":"IN"}},{"id":19608,"name":"Khatauli","state":{"id":1584},"country":{"id":105,"isocode2":"IN"}},{"id":19609,"name":"Khatauli Rural","state":{"id":1584},"country":{"id":105,"isocode2":"IN"}},{"id":19610,"name":"Khekra","state":{"id":1584},"country":{"id":105,"isocode2":"IN"}},{"id":19611,"name":"Kheri","state":{"id":1584},"country":{"id":105,"isocode2":"IN"}},{"id":19612,"name":"Kheta Sarai","state":{"id":1584},"country":{"id":105,"isocode2":"IN"}},{"id":19613,"name":"Khudaganj","state":{"id":1584},"country":{"id":105,"isocode2":"IN"}},{"id":19614,"name":"Khurja","state":{"id":1584},"country":{"id":105,"isocode2":"IN"}},{"id":19615,"name":"Khutar","state":{"id":1584},"country":{"id":105,"isocode2":"IN"}},{"id":19616,"name":"Kiraoli","state":{"id":1584},"country":{"id":105,"isocode2":"IN"}},{"id":19617,"name":"Kiratpur","state":{"id":1584},"country":{"id":105,"isocode2":"IN"}},{"id":19618,"name":"Kishanpur","state":{"id":1584},"country":{"id":105,"isocode2":"IN"}},{"id":19619,"name":"Kishni","state":{"id":1584},"country":{"id":105,"isocode2":"IN"}},{"id":19620,"name":"Kithaur","state":{"id":1584},"country":{"id":105,"isocode2":"IN"}},{"id":19621,"name":"Koiripur","state":{"id":1584},"country":{"id":105,"isocode2":"IN"}},{"id":19622,"name":"Konch","state":{"id":1584},"country":{"id":105,"isocode2":"IN"}},{"id":19623,"name":"Kopaganj","state":{"id":1584},"country":{"id":105,"isocode2":"IN"}},{"id":19624,"name":"Kora Jahanabad","state":{"id":1584},"country":{"id":105,"isocode2":"IN"}},{"id":19625,"name":"Korwa","state":{"id":1584},"country":{"id":105,"isocode2":"IN"}},{"id":19626,"name":"Kosi Kalan","state":{"id":1584},"country":{"id":105,"isocode2":"IN"}},{"id":19627,"name":"Kota","state":{"id":1584},"country":{"id":105,"isocode2":"IN"}},{"id":19628,"name":"Kotra","state":{"id":1584},"country":{"id":105,"isocode2":"IN"}},{"id":19629,"name":"Kotwa","state":{"id":1584},"country":{"id":105,"isocode2":"IN"}},{"id":19630,"name":"Kulpahar","state":{"id":1584},"country":{"id":105,"isocode2":"IN"}},{"id":19631,"name":"Kunda","state":{"id":1584},"country":{"id":105,"isocode2":"IN"}},{"id":19632,"name":"Kundarki","state":{"id":1584},"country":{"id":105,"isocode2":"IN"}},{"id":19633,"name":"Kunwargaon","state":{"id":1584},"country":{"id":105,"isocode2":"IN"}},{"id":19634,"name":"Kurara","state":{"id":1584},"country":{"id":105,"isocode2":"IN"}},{"id":19635,"name":"Kurawali","state":{"id":1584},"country":{"id":105,"isocode2":"IN"}},{"id":19636,"name":"Kursath","state":{"id":1584},"country":{"id":105,"isocode2":"IN"}},{"id":19637,"name":"Kurthi Jafarpur","state":{"id":1584},"country":{"id":105,"isocode2":"IN"}},{"id":19638,"name":"Kushinagar","state":{"id":1584},"country":{"id":105,"isocode2":"IN"}},{"id":19639,"name":"Kusmara","state":{"id":1584},"country":{"id":105,"isocode2":"IN"}},{"id":19640,"name":"Laharpur","state":{"id":1584},"country":{"id":105,"isocode2":"IN"}},{"id":19641,"name":"Lakhimpur","state":{"id":1584},"country":{"id":105,"isocode2":"IN"}},{"id":19642,"name":"Lakhna","state":{"id":1584},"country":{"id":105,"isocode2":"IN"}},{"id":19643,"name":"Lalganj","state":{"id":1584},"country":{"id":105,"isocode2":"IN"}},{"id":19644,"name":"Lalitpur","state":{"id":1584},"country":{"id":105,"isocode2":"IN"}},{"id":19645,"name":"Lar","state":{"id":1584},"country":{"id":105,"isocode2":"IN"}},{"id":19646,"name":"Lawar","state":{"id":1584},"country":{"id":105,"isocode2":"IN"}},{"id":19647,"name":"Ledwa Mahuwa","state":{"id":1584},"country":{"id":105,"isocode2":"IN"}},{"id":19648,"name":"Lohta","state":{"id":1584},"country":{"id":105,"isocode2":"IN"}},{"id":19649,"name":"Loni","state":{"id":1584},"country":{"id":105,"isocode2":"IN"}},{"id":19650,"name":"Lucknow","state":{"id":1584},"country":{"id":105,"isocode2":"IN"}},{"id":19651,"name":"Machhlishahr","state":{"id":1584},"country":{"id":105,"isocode2":"IN"}},{"id":19652,"name":"Madhoganj","state":{"id":1584},"country":{"id":105,"isocode2":"IN"}},{"id":19653,"name":"Madhogarh","state":{"id":1584},"country":{"id":105,"isocode2":"IN"}},{"id":19654,"name":"Maghar","state":{"id":1584},"country":{"id":105,"isocode2":"IN"}},{"id":19655,"name":"Mahaban","state":{"id":1584},"country":{"id":105,"isocode2":"IN"}},{"id":19656,"name":"Maharajganj","state":{"id":1584},"country":{"id":105,"isocode2":"IN"}},{"id":19657,"name":"Mahmudabad","state":{"id":1584},"country":{"id":105,"isocode2":"IN"}},{"id":19658,"name":"Mahoba","state":{"id":1584},"country":{"id":105,"isocode2":"IN"}},{"id":19659,"name":"Maholi","state":{"id":1584},"country":{"id":105,"isocode2":"IN"}},{"id":19660,"name":"Mahona","state":{"id":1584},"country":{"id":105,"isocode2":"IN"}},{"id":19661,"name":"Mahroni","state":{"id":1584},"country":{"id":105,"isocode2":"IN"}},{"id":19662,"name":"Mailani","state":{"id":1584},"country":{"id":105,"isocode2":"IN"}},{"id":19663,"name":"Mainpuri","state":{"id":1584},"country":{"id":105,"isocode2":"IN"}},{"id":19664,"name":"Majhara Pipar Ehatmali","state":{"id":1584},"country":{"id":105,"isocode2":"IN"}},{"id":19665,"name":"Majhauli Raj","state":{"id":1584},"country":{"id":105,"isocode2":"IN"}},{"id":19666,"name":"Malihabad","state":{"id":1584},"country":{"id":105,"isocode2":"IN"}},{"id":19667,"name":"Mallanwam","state":{"id":1584},"country":{"id":105,"isocode2":"IN"}},{"id":19668,"name":"Mandawar","state":{"id":1584},"country":{"id":105,"isocode2":"IN"}},{"id":19669,"name":"Manikpur","state":{"id":1584},"country":{"id":105,"isocode2":"IN"}},{"id":19670,"name":"Maniyar","state":{"id":1584},"country":{"id":105,"isocode2":"IN"}},{"id":19671,"name":"Manjhanpur","state":{"id":1584},"country":{"id":105,"isocode2":"IN"}},{"id":19672,"name":"Mankapur","state":{"id":1584},"country":{"id":105,"isocode2":"IN"}},{"id":19673,"name":"Marehra","state":{"id":1584},"country":{"id":105,"isocode2":"IN"}},{"id":19674,"name":"Mariahu","state":{"id":1584},"country":{"id":105,"isocode2":"IN"}},{"id":19675,"name":"Maruadih","state":{"id":1584},"country":{"id":105,"isocode2":"IN"}},{"id":19676,"name":"Maswasi","state":{"id":1584},"country":{"id":105,"isocode2":"IN"}},{"id":19677,"name":"Mataundh","state":{"id":1584},"country":{"id":105,"isocode2":"IN"}},{"id":19678,"name":"Mathu","state":{"id":1584},"country":{"id":105,"isocode2":"IN"}},{"id":19679,"name":"Mathura","state":{"id":1584},"country":{"id":105,"isocode2":"IN"}},{"id":19680,"name":"Mathura Cantonment","state":{"id":1584},"country":{"id":105,"isocode2":"IN"}},{"id":19681,"name":"Mau","state":{"id":1584},"country":{"id":105,"isocode2":"IN"}},{"id":19682,"name":"Mau Aima","state":{"id":1584},"country":{"id":105,"isocode2":"IN"}},{"id":19683,"name":"Maudaha","state":{"id":1584},"country":{"id":105,"isocode2":"IN"}},{"id":19684,"name":"Mauranipur","state":{"id":1584},"country":{"id":105,"isocode2":"IN"}},{"id":19685,"name":"Maurawan","state":{"id":1584},"country":{"id":105,"isocode2":"IN"}},{"id":19686,"name":"Mawana","state":{"id":1584},"country":{"id":105,"isocode2":"IN"}},{"id":19687,"name":"Meerut","state":{"id":1584},"country":{"id":105,"isocode2":"IN"}},{"id":19688,"name":"Mehnagar","state":{"id":1584},"country":{"id":105,"isocode2":"IN"}},{"id":19689,"name":"Mehndawal","state":{"id":1584},"country":{"id":105,"isocode2":"IN"}},{"id":19690,"name":"Mendu","state":{"id":1584},"country":{"id":105,"isocode2":"IN"}},{"id":19691,"name":"Milak","state":{"id":1584},"country":{"id":105,"isocode2":"IN"}},{"id":19692,"name":"Miranpur","state":{"id":1584},"country":{"id":105,"isocode2":"IN"}},{"id":19693,"name":"Mirat","state":{"id":1584},"country":{"id":105,"isocode2":"IN"}},{"id":19694,"name":"Mirat Cantonment","state":{"id":1584},"country":{"id":105,"isocode2":"IN"}},{"id":19695,"name":"Mirganj","state":{"id":1584},"country":{"id":105,"isocode2":"IN"}},{"id":19696,"name":"Mirzapur","state":{"id":1584},"country":{"id":105,"isocode2":"IN"}},{"id":19697,"name":"Misrikh","state":{"id":1584},"country":{"id":105,"isocode2":"IN"}},{"id":19698,"name":"Modinagar","state":{"id":1584},"country":{"id":105,"isocode2":"IN"}},{"id":19699,"name":"Mogra Badshahpur","state":{"id":1584},"country":{"id":105,"isocode2":"IN"}},{"id":19700,"name":"Mohan","state":{"id":1584},"country":{"id":105,"isocode2":"IN"}},{"id":19701,"name":"Mohanpur","state":{"id":1584},"country":{"id":105,"isocode2":"IN"}},{"id":19702,"name":"Mohiuddinpur","state":{"id":1584},"country":{"id":105,"isocode2":"IN"}},{"id":19703,"name":"Moradabad","state":{"id":1584},"country":{"id":105,"isocode2":"IN"}},{"id":19704,"name":"Moth","state":{"id":1584},"country":{"id":105,"isocode2":"IN"}},{"id":19705,"name":"Mubarakpur","state":{"id":1584},"country":{"id":105,"isocode2":"IN"}},{"id":19706,"name":"Mughal Sarai","state":{"id":1584},"country":{"id":105,"isocode2":"IN"}},{"id":19707,"name":"Mughal Sarai Railway Settlemen","state":{"id":1584},"country":{"id":105,"isocode2":"IN"}},{"id":19708,"name":"Muhammadabad","state":{"id":1584},"country":{"id":105,"isocode2":"IN"}},{"id":19709,"name":"Muhammadi","state":{"id":1584},"country":{"id":105,"isocode2":"IN"}},{"id":19710,"name":"Mukrampur Khema","state":{"id":1584},"country":{"id":105,"isocode2":"IN"}},{"id":19711,"name":"Mundia","state":{"id":1584},"country":{"id":105,"isocode2":"IN"}},{"id":19712,"name":"Mundora","state":{"id":1584},"country":{"id":105,"isocode2":"IN"}},{"id":19713,"name":"Muradnagar","state":{"id":1584},"country":{"id":105,"isocode2":"IN"}},{"id":19714,"name":"Mursan","state":{"id":1584},"country":{"id":105,"isocode2":"IN"}},{"id":19715,"name":"Musafirkhana","state":{"id":1584},"country":{"id":105,"isocode2":"IN"}},{"id":19716,"name":"Muzaffarnagar","state":{"id":1584},"country":{"id":105,"isocode2":"IN"}},{"id":19717,"name":"Nadigaon","state":{"id":1584},"country":{"id":105,"isocode2":"IN"}},{"id":19718,"name":"Nagina","state":{"id":1584},"country":{"id":105,"isocode2":"IN"}},{"id":19719,"name":"Nagram","state":{"id":1584},"country":{"id":105,"isocode2":"IN"}},{"id":19720,"name":"Nai Bazar","state":{"id":1584},"country":{"id":105,"isocode2":"IN"}},{"id":19721,"name":"Nainana Jat","state":{"id":1584},"country":{"id":105,"isocode2":"IN"}},{"id":19722,"name":"Najibabad","state":{"id":1584},"country":{"id":105,"isocode2":"IN"}},{"id":19723,"name":"Nakur","state":{"id":1584},"country":{"id":105,"isocode2":"IN"}},{"id":19724,"name":"Nanaunta","state":{"id":1584},"country":{"id":105,"isocode2":"IN"}},{"id":19725,"name":"Nandgaon","state":{"id":1584},"country":{"id":105,"isocode2":"IN"}},{"id":19726,"name":"Nanpara","state":{"id":1584},"country":{"id":105,"isocode2":"IN"}},{"id":19727,"name":"Naraini","state":{"id":1584},"country":{"id":105,"isocode2":"IN"}},{"id":19728,"name":"Narauli","state":{"id":1584},"country":{"id":105,"isocode2":"IN"}},{"id":19729,"name":"Naraura","state":{"id":1584},"country":{"id":105,"isocode2":"IN"}},{"id":19730,"name":"Naugawan Sadat","state":{"id":1584},"country":{"id":105,"isocode2":"IN"}},{"id":19731,"name":"Nautanwa","state":{"id":1584},"country":{"id":105,"isocode2":"IN"}},{"id":19732,"name":"Nawabganj","state":{"id":1584},"country":{"id":105,"isocode2":"IN"}},{"id":19733,"name":"Nichlaul","state":{"id":1584},"country":{"id":105,"isocode2":"IN"}},{"id":19734,"name":"Nidhauli Kalan","state":{"id":1584},"country":{"id":105,"isocode2":"IN"}},{"id":19735,"name":"Nihtaur","state":{"id":1584},"country":{"id":105,"isocode2":"IN"}},{"id":19736,"name":"Nindaura","state":{"id":1584},"country":{"id":105,"isocode2":"IN"}},{"id":19737,"name":"Niwari","state":{"id":1584},"country":{"id":105,"isocode2":"IN"}},{"id":19738,"name":"Nizamabad","state":{"id":1584},"country":{"id":105,"isocode2":"IN"}},{"id":19739,"name":"Noida","state":{"id":1584},"country":{"id":105,"isocode2":"IN"}},{"id":19740,"name":"Northern Railway Colony","state":{"id":1584},"country":{"id":105,"isocode2":"IN"}},{"id":19741,"name":"Nurpur","state":{"id":1584},"country":{"id":105,"isocode2":"IN"}},{"id":19742,"name":"Nyoria Husenpur","state":{"id":1584},"country":{"id":105,"isocode2":"IN"}},{"id":19743,"name":"Nyotini","state":{"id":1584},"country":{"id":105,"isocode2":"IN"}},{"id":19744,"name":"Obra","state":{"id":1584},"country":{"id":105,"isocode2":"IN"}},{"id":19745,"name":"Oel Dhakwa","state":{"id":1584},"country":{"id":105,"isocode2":"IN"}},{"id":19746,"name":"Orai","state":{"id":1584},"country":{"id":105,"isocode2":"IN"}},{"id":19747,"name":"Oran","state":{"id":1584},"country":{"id":105,"isocode2":"IN"}},{"id":19748,"name":"Ordinance Factory Muradnagar","state":{"id":1584},"country":{"id":105,"isocode2":"IN"}},{"id":19749,"name":"Pachperwa","state":{"id":1584},"country":{"id":105,"isocode2":"IN"}},{"id":19750,"name":"Padrauna","state":{"id":1584},"country":{"id":105,"isocode2":"IN"}},{"id":19751,"name":"Pahasu","state":{"id":1584},"country":{"id":105,"isocode2":"IN"}},{"id":19752,"name":"Paintepur","state":{"id":1584},"country":{"id":105,"isocode2":"IN"}},{"id":19753,"name":"Pali","state":{"id":1584},"country":{"id":105,"isocode2":"IN"}},{"id":19754,"name":"Palia Kalan","state":{"id":1584},"country":{"id":105,"isocode2":"IN"}},{"id":19755,"name":"Parasi","state":{"id":1584},"country":{"id":105,"isocode2":"IN"}},{"id":19756,"name":"Parichha","state":{"id":1584},"country":{"id":105,"isocode2":"IN"}},{"id":19757,"name":"Parichhatgarh","state":{"id":1584},"country":{"id":105,"isocode2":"IN"}},{"id":19758,"name":"Parsadepur","state":{"id":1584},"country":{"id":105,"isocode2":"IN"}},{"id":19759,"name":"Patala","state":{"id":1584},"country":{"id":105,"isocode2":"IN"}},{"id":19760,"name":"Patiyali","state":{"id":1584},"country":{"id":105,"isocode2":"IN"}},{"id":19761,"name":"Patti","state":{"id":1584},"country":{"id":105,"isocode2":"IN"}},{"id":19762,"name":"Pawayan","state":{"id":1584},"country":{"id":105,"isocode2":"IN"}},{"id":19763,"name":"Phalauda","state":{"id":1584},"country":{"id":105,"isocode2":"IN"}},{"id":19764,"name":"Phaphund","state":{"id":1584},"country":{"id":105,"isocode2":"IN"}},{"id":19765,"name":"Phulpur","state":{"id":1584},"country":{"id":105,"isocode2":"IN"}},{"id":19766,"name":"Phulwaria","state":{"id":1584},"country":{"id":105,"isocode2":"IN"}},{"id":19767,"name":"Pihani","state":{"id":1584},"country":{"id":105,"isocode2":"IN"}},{"id":19768,"name":"Pilibhit","state":{"id":1584},"country":{"id":105,"isocode2":"IN"}},{"id":19769,"name":"Pilkana","state":{"id":1584},"country":{"id":105,"isocode2":"IN"}},{"id":19770,"name":"Pilkhuwa","state":{"id":1584},"country":{"id":105,"isocode2":"IN"}},{"id":19771,"name":"Pinahat","state":{"id":1584},"country":{"id":105,"isocode2":"IN"}},{"id":19772,"name":"Pipalsana Chaudhari","state":{"id":1584},"country":{"id":105,"isocode2":"IN"}},{"id":19773,"name":"Pipiganj","state":{"id":1584},"country":{"id":105,"isocode2":"IN"}},{"id":19774,"name":"Pipraich","state":{"id":1584},"country":{"id":105,"isocode2":"IN"}},{"id":19775,"name":"Pipri","state":{"id":1584},"country":{"id":105,"isocode2":"IN"}},{"id":19776,"name":"Pratapgarh","state":{"id":1584},"country":{"id":105,"isocode2":"IN"}},{"id":19777,"name":"Pukhrayan","state":{"id":1584},"country":{"id":105,"isocode2":"IN"}},{"id":19778,"name":"Puranpur","state":{"id":1584},"country":{"id":105,"isocode2":"IN"}},{"id":19779,"name":"Purdil Nagar","state":{"id":1584},"country":{"id":105,"isocode2":"IN"}},{"id":19780,"name":"Purqazi","state":{"id":1584},"country":{"id":105,"isocode2":"IN"}},{"id":19781,"name":"Purwa","state":{"id":1584},"country":{"id":105,"isocode2":"IN"}},{"id":19782,"name":"Qasimpur","state":{"id":1584},"country":{"id":105,"isocode2":"IN"}},{"id":19783,"name":"Rabupura","state":{"id":1584},"country":{"id":105,"isocode2":"IN"}},{"id":19784,"name":"Radha Kund","state":{"id":1584},"country":{"id":105,"isocode2":"IN"}},{"id":19785,"name":"Rae Bareilly","state":{"id":1584},"country":{"id":105,"isocode2":"IN"}},{"id":19786,"name":"Raja Ka Rampur","state":{"id":1584},"country":{"id":105,"isocode2":"IN"}},{"id":19787,"name":"Rajapur","state":{"id":1584},"country":{"id":105,"isocode2":"IN"}},{"id":19788,"name":"Ramkola","state":{"id":1584},"country":{"id":105,"isocode2":"IN"}},{"id":19789,"name":"Ramnagar","state":{"id":1584},"country":{"id":105,"isocode2":"IN"}},{"id":19790,"name":"Rampur","state":{"id":1584},"country":{"id":105,"isocode2":"IN"}},{"id":19791,"name":"Rampur Bhawanipur","state":{"id":1584},"country":{"id":105,"isocode2":"IN"}},{"id":19792,"name":"Rampur Karkhana","state":{"id":1584},"country":{"id":105,"isocode2":"IN"}},{"id":19793,"name":"Rampur Maniharan","state":{"id":1584},"country":{"id":105,"isocode2":"IN"}},{"id":19794,"name":"Rampura","state":{"id":1584},"country":{"id":105,"isocode2":"IN"}},{"id":19795,"name":"Ranipur","state":{"id":1584},"country":{"id":105,"isocode2":"IN"}},{"id":19796,"name":"Rashidpur Garhi","state":{"id":1584},"country":{"id":105,"isocode2":"IN"}},{"id":19797,"name":"Rasra","state":{"id":1584},"country":{"id":105,"isocode2":"IN"}},{"id":19798,"name":"Rasulabad","state":{"id":1584},"country":{"id":105,"isocode2":"IN"}},{"id":19799,"name":"Rath","state":{"id":1584},"country":{"id":105,"isocode2":"IN"}},{"id":19800,"name":"Raya","state":{"id":1584},"country":{"id":105,"isocode2":"IN"}},{"id":19801,"name":"Renukut","state":{"id":1584},"country":{"id":105,"isocode2":"IN"}},{"id":19802,"name":"Reoti","state":{"id":1584},"country":{"id":105,"isocode2":"IN"}},{"id":19803,"name":"Richha","state":{"id":1584},"country":{"id":105,"isocode2":"IN"}},{"id":19804,"name":"Risia Bazar","state":{"id":1584},"country":{"id":105,"isocode2":"IN"}},{"id":19805,"name":"Rithora","state":{"id":1584},"country":{"id":105,"isocode2":"IN"}},{"id":19806,"name":"Robertsganj","state":{"id":1584},"country":{"id":105,"isocode2":"IN"}},{"id":19807,"name":"Roza","state":{"id":1584},"country":{"id":105,"isocode2":"IN"}},{"id":19808,"name":"Rudarpur","state":{"id":1584},"country":{"id":105,"isocode2":"IN"}},{"id":19809,"name":"Rudauli","state":{"id":1584},"country":{"id":105,"isocode2":"IN"}},{"id":19810,"name":"Rudayan","state":{"id":1584},"country":{"id":105,"isocode2":"IN"}},{"id":19811,"name":"Rura","state":{"id":1584},"country":{"id":105,"isocode2":"IN"}},{"id":19812,"name":"Rustamnagar Sahaspur","state":{"id":1584},"country":{"id":105,"isocode2":"IN"}},{"id":19813,"name":"Sabatwar","state":{"id":1584},"country":{"id":105,"isocode2":"IN"}},{"id":19814,"name":"Sadabad","state":{"id":1584},"country":{"id":105,"isocode2":"IN"}},{"id":19815,"name":"Sadat","state":{"id":1584},"country":{"id":105,"isocode2":"IN"}},{"id":19816,"name":"Safipur","state":{"id":1584},"country":{"id":105,"isocode2":"IN"}},{"id":19817,"name":"Sahanpur","state":{"id":1584},"country":{"id":105,"isocode2":"IN"}},{"id":19818,"name":"Saharanpur","state":{"id":1584},"country":{"id":105,"isocode2":"IN"}},{"id":19819,"name":"Sahaspur","state":{"id":1584},"country":{"id":105,"isocode2":"IN"}},{"id":19820,"name":"Sahaswan","state":{"id":1584},"country":{"id":105,"isocode2":"IN"}},{"id":19821,"name":"Sahawar","state":{"id":1584},"country":{"id":105,"isocode2":"IN"}},{"id":19822,"name":"Sahibabad","state":{"id":1584},"country":{"id":105,"isocode2":"IN"}},{"id":19823,"name":"Sahjanwa","state":{"id":1584},"country":{"id":105,"isocode2":"IN"}},{"id":19824,"name":"Sahpau","state":{"id":1584},"country":{"id":105,"isocode2":"IN"}},{"id":19825,"name":"Saidpur","state":{"id":1584},"country":{"id":105,"isocode2":"IN"}},{"id":19826,"name":"Sainthal","state":{"id":1584},"country":{"id":105,"isocode2":"IN"}},{"id":19827,"name":"Saiyadraja","state":{"id":1584},"country":{"id":105,"isocode2":"IN"}},{"id":19828,"name":"Sakhanu","state":{"id":1584},"country":{"id":105,"isocode2":"IN"}},{"id":19829,"name":"Sakit","state":{"id":1584},"country":{"id":105,"isocode2":"IN"}},{"id":19830,"name":"Salarpur Khadar","state":{"id":1584},"country":{"id":105,"isocode2":"IN"}},{"id":19831,"name":"Salimpur","state":{"id":1584},"country":{"id":105,"isocode2":"IN"}},{"id":19832,"name":"Salon","state":{"id":1584},"country":{"id":105,"isocode2":"IN"}},{"id":19833,"name":"Sambhal","state":{"id":1584},"country":{"id":105,"isocode2":"IN"}},{"id":19834,"name":"Sambhawali","state":{"id":1584},"country":{"id":105,"isocode2":"IN"}},{"id":19835,"name":"Samdhan","state":{"id":1584},"country":{"id":105,"isocode2":"IN"}},{"id":19836,"name":"Samthar","state":{"id":1584},"country":{"id":105,"isocode2":"IN"}},{"id":19837,"name":"Sandi","state":{"id":1584},"country":{"id":105,"isocode2":"IN"}},{"id":19838,"name":"Sandila","state":{"id":1584},"country":{"id":105,"isocode2":"IN"}},{"id":19839,"name":"Sarai Mir","state":{"id":1584},"country":{"id":105,"isocode2":"IN"}},{"id":19840,"name":"Sarai akil","state":{"id":1584},"country":{"id":105,"isocode2":"IN"}},{"id":19841,"name":"Sarauli","state":{"id":1584},"country":{"id":105,"isocode2":"IN"}},{"id":19842,"name":"Sardhana","state":{"id":1584},"country":{"id":105,"isocode2":"IN"}},{"id":19843,"name":"Sarila","state":{"id":1584},"country":{"id":105,"isocode2":"IN"}},{"id":19844,"name":"Sarsawan","state":{"id":1584},"country":{"id":105,"isocode2":"IN"}},{"id":19845,"name":"Sasni","state":{"id":1584},"country":{"id":105,"isocode2":"IN"}},{"id":19846,"name":"Satrikh","state":{"id":1584},"country":{"id":105,"isocode2":"IN"}},{"id":19847,"name":"Saunkh","state":{"id":1584},"country":{"id":105,"isocode2":"IN"}},{"id":19848,"name":"Saurikh","state":{"id":1584},"country":{"id":105,"isocode2":"IN"}},{"id":19849,"name":"Seohara","state":{"id":1584},"country":{"id":105,"isocode2":"IN"}},{"id":19850,"name":"Sewal Khas","state":{"id":1584},"country":{"id":105,"isocode2":"IN"}},{"id":19851,"name":"Sewarhi","state":{"id":1584},"country":{"id":105,"isocode2":"IN"}},{"id":19852,"name":"Shahabad","state":{"id":1584},"country":{"id":105,"isocode2":"IN"}},{"id":19853,"name":"Shahganj","state":{"id":1584},"country":{"id":105,"isocode2":"IN"}},{"id":19854,"name":"Shahi","state":{"id":1584},"country":{"id":105,"isocode2":"IN"}},{"id":19855,"name":"Shahjahanpur","state":{"id":1584},"country":{"id":105,"isocode2":"IN"}},{"id":19856,"name":"Shahjahanpur Cantonment","state":{"id":1584},"country":{"id":105,"isocode2":"IN"}},{"id":19857,"name":"Shahpur","state":{"id":1584},"country":{"id":105,"isocode2":"IN"}},{"id":19858,"name":"Shamli","state":{"id":1584},"country":{"id":105,"isocode2":"IN"}},{"id":19859,"name":"Shamsabad","state":{"id":1584},"country":{"id":105,"isocode2":"IN"}},{"id":19860,"name":"Shankargarh","state":{"id":1584},"country":{"id":105,"isocode2":"IN"}},{"id":19861,"name":"Shergarh","state":{"id":1584},"country":{"id":105,"isocode2":"IN"}},{"id":19862,"name":"Sherkot","state":{"id":1584},"country":{"id":105,"isocode2":"IN"}},{"id":19863,"name":"Shikarpur","state":{"id":1584},"country":{"id":105,"isocode2":"IN"}},{"id":19864,"name":"Shikohabad","state":{"id":1584},"country":{"id":105,"isocode2":"IN"}},{"id":19865,"name":"Shisgarh","state":{"id":1584},"country":{"id":105,"isocode2":"IN"}},{"id":19866,"name":"Shivdaspur","state":{"id":1584},"country":{"id":105,"isocode2":"IN"}},{"id":19867,"name":"Shivli","state":{"id":1584},"country":{"id":105,"isocode2":"IN"}},{"id":19868,"name":"Shivrajpur","state":{"id":1584},"country":{"id":105,"isocode2":"IN"}},{"id":19869,"name":"Shohratgarh","state":{"id":1584},"country":{"id":105,"isocode2":"IN"}},{"id":19870,"name":"Siddhanur","state":{"id":1584},"country":{"id":105,"isocode2":"IN"}},{"id":19871,"name":"Siddharthnagar","state":{"id":1584},"country":{"id":105,"isocode2":"IN"}},{"id":19872,"name":"Sidhauli","state":{"id":1584},"country":{"id":105,"isocode2":"IN"}},{"id":19873,"name":"Sidhpura","state":{"id":1584},"country":{"id":105,"isocode2":"IN"}},{"id":19874,"name":"Sikandarabad","state":{"id":1584},"country":{"id":105,"isocode2":"IN"}},{"id":19875,"name":"Sikandarpur","state":{"id":1584},"country":{"id":105,"isocode2":"IN"}},{"id":19876,"name":"Sikandra","state":{"id":1584},"country":{"id":105,"isocode2":"IN"}},{"id":19877,"name":"Sikandra Rao","state":{"id":1584},"country":{"id":105,"isocode2":"IN"}},{"id":19878,"name":"Singahi Bhiraura","state":{"id":1584},"country":{"id":105,"isocode2":"IN"}},{"id":19879,"name":"Sirathu","state":{"id":1584},"country":{"id":105,"isocode2":"IN"}},{"id":19880,"name":"Sirsa","state":{"id":1584},"country":{"id":105,"isocode2":"IN"}},{"id":19881,"name":"Sirsaganj","state":{"id":1584},"country":{"id":105,"isocode2":"IN"}},{"id":19882,"name":"Sirsi","state":{"id":1584},"country":{"id":105,"isocode2":"IN"}},{"id":19883,"name":"Sisauli","state":{"id":1584},"country":{"id":105,"isocode2":"IN"}},{"id":19884,"name":"Siswa Bazar","state":{"id":1584},"country":{"id":105,"isocode2":"IN"}},{"id":19885,"name":"Sitapur","state":{"id":1584},"country":{"id":105,"isocode2":"IN"}},{"id":19886,"name":"Siyana","state":{"id":1584},"country":{"id":105,"isocode2":"IN"}},{"id":19887,"name":"Som","state":{"id":1584},"country":{"id":105,"isocode2":"IN"}},{"id":19888,"name":"Sonbhadra","state":{"id":1584},"country":{"id":105,"isocode2":"IN"}},{"id":19889,"name":"Soron","state":{"id":1584},"country":{"id":105,"isocode2":"IN"}},{"id":19890,"name":"Suar","state":{"id":1584},"country":{"id":105,"isocode2":"IN"}},{"id":19891,"name":"Sukhmalpur Nizamabad","state":{"id":1584},"country":{"id":105,"isocode2":"IN"}},{"id":19892,"name":"Sultanpur","state":{"id":1584},"country":{"id":105,"isocode2":"IN"}},{"id":19893,"name":"Sumerpur","state":{"id":1584},"country":{"id":105,"isocode2":"IN"}},{"id":19894,"name":"Suriyawan","state":{"id":1584},"country":{"id":105,"isocode2":"IN"}},{"id":19895,"name":"Swamibagh","state":{"id":1584},"country":{"id":105,"isocode2":"IN"}},{"id":19896,"name":"Tajpur","state":{"id":1584},"country":{"id":105,"isocode2":"IN"}},{"id":19897,"name":"Talbahat","state":{"id":1584},"country":{"id":105,"isocode2":"IN"}},{"id":19898,"name":"Talgram","state":{"id":1584},"country":{"id":105,"isocode2":"IN"}},{"id":19899,"name":"Tambaur","state":{"id":1584},"country":{"id":105,"isocode2":"IN"}},{"id":19900,"name":"Tanda","state":{"id":1584},"country":{"id":105,"isocode2":"IN"}},{"id":19901,"name":"Tatarpur Lallu","state":{"id":1584},"country":{"id":105,"isocode2":"IN"}},{"id":19902,"name":"Tetribazar","state":{"id":1584},"country":{"id":105,"isocode2":"IN"}},{"id":19903,"name":"Thakurdwara","state":{"id":1584},"country":{"id":105,"isocode2":"IN"}},{"id":19904,"name":"Thana Bhawan","state":{"id":1584},"country":{"id":105,"isocode2":"IN"}},{"id":19905,"name":"Thiriya Nizamat Khan","state":{"id":1584},"country":{"id":105,"isocode2":"IN"}},{"id":19906,"name":"Tikaitnagar","state":{"id":1584},"country":{"id":105,"isocode2":"IN"}},{"id":19907,"name":"Tikri","state":{"id":1584},"country":{"id":105,"isocode2":"IN"}},{"id":19908,"name":"Tilhar","state":{"id":1584},"country":{"id":105,"isocode2":"IN"}},{"id":19909,"name":"Tindwari","state":{"id":1584},"country":{"id":105,"isocode2":"IN"}},{"id":19910,"name":"Tirwaganj","state":{"id":1584},"country":{"id":105,"isocode2":"IN"}},{"id":19911,"name":"Titron","state":{"id":1584},"country":{"id":105,"isocode2":"IN"}},{"id":19912,"name":"Tori Fatehpur","state":{"id":1584},"country":{"id":105,"isocode2":"IN"}},{"id":19913,"name":"Tulsipur","state":{"id":1584},"country":{"id":105,"isocode2":"IN"}},{"id":19914,"name":"Tundla","state":{"id":1584},"country":{"id":105,"isocode2":"IN"}},{"id":19915,"name":"Tundla Kham","state":{"id":1584},"country":{"id":105,"isocode2":"IN"}},{"id":19916,"name":"Tundla Railway Colony","state":{"id":1584},"country":{"id":105,"isocode2":"IN"}},{"id":19917,"name":"Ugu","state":{"id":1584},"country":{"id":105,"isocode2":"IN"}},{"id":19918,"name":"Ujhani","state":{"id":1584},"country":{"id":105,"isocode2":"IN"}},{"id":19919,"name":"Ujhari","state":{"id":1584},"country":{"id":105,"isocode2":"IN"}},{"id":19920,"name":"Umri","state":{"id":1584},"country":{"id":105,"isocode2":"IN"}},{"id":19921,"name":"Umri Kalan","state":{"id":1584},"country":{"id":105,"isocode2":"IN"}},{"id":19922,"name":"Un","state":{"id":1584},"country":{"id":105,"isocode2":"IN"}},{"id":19923,"name":"Unchahar","state":{"id":1584},"country":{"id":105,"isocode2":"IN"}},{"id":19924,"name":"Unnao","state":{"id":1584},"country":{"id":105,"isocode2":"IN"}},{"id":19925,"name":"Usaihat","state":{"id":1584},"country":{"id":105,"isocode2":"IN"}},{"id":19926,"name":"Usawan","state":{"id":1584},"country":{"id":105,"isocode2":"IN"}},{"id":19927,"name":"Utraula","state":{"id":1584},"country":{"id":105,"isocode2":"IN"}},{"id":19928,"name":"Varanasi","state":{"id":1584},"country":{"id":105,"isocode2":"IN"}},{"id":19929,"name":"Varanasi Cantonment","state":{"id":1584},"country":{"id":105,"isocode2":"IN"}},{"id":19930,"name":"Vijaigarh","state":{"id":1584},"country":{"id":105,"isocode2":"IN"}},{"id":19931,"name":"Vrindavan","state":{"id":1584},"country":{"id":105,"isocode2":"IN"}},{"id":19932,"name":"Wazirganj","state":{"id":1584},"country":{"id":105,"isocode2":"IN"}},{"id":19933,"name":"Zafarabad","state":{"id":1584},"country":{"id":105,"isocode2":"IN"}},{"id":19934,"name":"Zaidpur","state":{"id":1584},"country":{"id":105,"isocode2":"IN"}},{"id":19935,"name":"Zamania","state":{"id":1584},"country":{"id":105,"isocode2":"IN"}}]