[{"id":5171,"name":"Alhue","state":{"id":666},"country":{"id":48,"isocode2":"CL"}},{"id":5172,"name":"Buin","state":{"id":666},"country":{"id":48,"isocode2":"CL"}},{"id":5173,"name":"Calera de Tango","state":{"id":666},"country":{"id":48,"isocode2":"CL"}},{"id":5174,"name":"Colina","state":{"id":666},"country":{"id":48,"isocode2":"CL"}},{"id":5175,"name":"Curacavi","state":{"id":666},"country":{"id":48,"isocode2":"CL"}},{"id":5176,"name":"El Monte","state":{"id":666},"country":{"id":48,"isocode2":"CL"}},{"id":5177,"name":"Isla de Maipo","state":{"id":666},"country":{"id":48,"isocode2":"CL"}},{"id":5178,"name":"Lampa","state":{"id":666},"country":{"id":48,"isocode2":"CL"}},{"id":5179,"name":"Maria Pinto","state":{"id":666},"country":{"id":48,"isocode2":"CL"}},{"id":5180,"name":"Melipilla","state":{"id":666},"country":{"id":48,"isocode2":"CL"}},{"id":5181,"name":"Padre Hurtado","state":{"id":666},"country":{"id":48,"isocode2":"CL"}},{"id":5182,"name":"Paine","state":{"id":666},"country":{"id":48,"isocode2":"CL"}},{"id":5183,"name":"Penaflor","state":{"id":666},"country":{"id":48,"isocode2":"CL"}},{"id":5184,"name":"Pirque","state":{"id":666},"country":{"id":48,"isocode2":"CL"}},{"id":5185,"name":"Puente Alto","state":{"id":666},"country":{"id":48,"isocode2":"CL"}},{"id":5186,"name":"Quilicura","state":{"id":666},"country":{"id":48,"isocode2":"CL"}},{"id":5187,"name":"San Bernardo","state":{"id":666},"country":{"id":48,"isocode2":"CL"}},{"id":5188,"name":"San Jose de Maipo","state":{"id":666},"country":{"id":48,"isocode2":"CL"}},{"id":5189,"name":"San Pedro","state":{"id":666},"country":{"id":48,"isocode2":"CL"}},{"id":5190,"name":"Santiago","state":{"id":666},"country":{"id":48,"isocode2":"CL"}},{"id":5191,"name":"Talagante","state":{"id":666},"country":{"id":48,"isocode2":"CL"}},{"id":5192,"name":"Tiltil","state":{"id":666},"country":{"id":48,"isocode2":"CL"}}]