[{"id":4004,"name":"Central","country":{"id":249,"isocode2":"ZM"}},{"id":4005,"name":"Copperbelt","country":{"id":249,"isocode2":"ZM"}},{"id":4006,"name":"Eastern","country":{"id":249,"isocode2":"ZM"}},{"id":4007,"name":"Luapala","country":{"id":249,"isocode2":"ZM"}},{"id":4008,"name":"Lusaka","country":{"id":249,"isocode2":"ZM"}},{"id":4009,"name":"North-Western","country":{"id":249,"isocode2":"ZM"}},{"id":4010,"name":"Northern","country":{"id":249,"isocode2":"ZM"}},{"id":4011,"name":"Southern","country":{"id":249,"isocode2":"ZM"}},{"id":4012,"name":"Western","country":{"id":249,"isocode2":"ZM"}}]