[{"id":798,"name":"Central Bohemian","country":{"id":62,"isocode2":"CZ"}},{"id":799,"name":"Frycovice","country":{"id":62,"isocode2":"CZ"}},{"id":800,"name":"Jihocesky Kraj","country":{"id":62,"isocode2":"CZ"}},{"id":801,"name":"Jihochesky","country":{"id":62,"isocode2":"CZ"}},{"id":802,"name":"Jihomoravsky","country":{"id":62,"isocode2":"CZ"}},{"id":803,"name":"Karlovarsky","country":{"id":62,"isocode2":"CZ"}},{"id":804,"name":"Klecany","country":{"id":62,"isocode2":"CZ"}},{"id":805,"name":"Kralovehradecky","country":{"id":62,"isocode2":"CZ"}},{"id":806,"name":"Liberecky","country":{"id":62,"isocode2":"CZ"}},{"id":807,"name":"Lipov","country":{"id":62,"isocode2":"CZ"}},{"id":808,"name":"Moravskoslezsky","country":{"id":62,"isocode2":"CZ"}},{"id":809,"name":"Olomoucky","country":{"id":62,"isocode2":"CZ"}},{"id":810,"name":"Olomoucky Kraj","country":{"id":62,"isocode2":"CZ"}},{"id":811,"name":"Pardubicky","country":{"id":62,"isocode2":"CZ"}},{"id":812,"name":"Plzensky","country":{"id":62,"isocode2":"CZ"}},{"id":813,"name":"Praha","country":{"id":62,"isocode2":"CZ"}},{"id":814,"name":"Rajhrad","country":{"id":62,"isocode2":"CZ"}},{"id":815,"name":"Smirice","country":{"id":62,"isocode2":"CZ"}},{"id":816,"name":"South Moravian","country":{"id":62,"isocode2":"CZ"}},{"id":817,"name":"Straz nad Nisou","country":{"id":62,"isocode2":"CZ"}},{"id":818,"name":"Stredochesky","country":{"id":62,"isocode2":"CZ"}},{"id":819,"name":"Unicov","country":{"id":62,"isocode2":"CZ"}},{"id":820,"name":"Ustecky","country":{"id":62,"isocode2":"CZ"}},{"id":821,"name":"Valletta","country":{"id":62,"isocode2":"CZ"}},{"id":822,"name":"Velesin","country":{"id":62,"isocode2":"CZ"}},{"id":823,"name":"Vysochina","country":{"id":62,"isocode2":"CZ"}},{"id":824,"name":"Zlinsky","country":{"id":62,"isocode2":"CZ"}}]