[{"id":2599,"name":"Akershus","country":{"id":168,"isocode2":"NO"}},{"id":2600,"name":"Aust Agder","country":{"id":168,"isocode2":"NO"}},{"id":2601,"name":"Bergen","country":{"id":168,"isocode2":"NO"}},{"id":2602,"name":"Buskerud","country":{"id":168,"isocode2":"NO"}},{"id":2603,"name":"Finnmark","country":{"id":168,"isocode2":"NO"}},{"id":2604,"name":"Hedmark","country":{"id":168,"isocode2":"NO"}},{"id":2605,"name":"Hordaland","country":{"id":168,"isocode2":"NO"}},{"id":2606,"name":"Moere og Romsdal","country":{"id":168,"isocode2":"NO"}},{"id":2607,"name":"Nord Trondelag","country":{"id":168,"isocode2":"NO"}},{"id":2608,"name":"Nordland","country":{"id":168,"isocode2":"NO"}},{"id":2609,"name":"Oestfold","country":{"id":168,"isocode2":"NO"}},{"id":2610,"name":"Oppland","country":{"id":168,"isocode2":"NO"}},{"id":2611,"name":"Oslo","country":{"id":168,"isocode2":"NO"}},{"id":2612,"name":"Rogaland","country":{"id":168,"isocode2":"NO"}},{"id":2613,"name":"Soer Troendelag","country":{"id":168,"isocode2":"NO"}},{"id":2614,"name":"Sogn og Fjordane","country":{"id":168,"isocode2":"NO"}},{"id":2615,"name":"Stavern","country":{"id":168,"isocode2":"NO"}},{"id":2616,"name":"Sykkylven","country":{"id":168,"isocode2":"NO"}},{"id":2617,"name":"Telemark","country":{"id":168,"isocode2":"NO"}},{"id":2618,"name":"Troms","country":{"id":168,"isocode2":"NO"}},{"id":2619,"name":"Vest Agder","country":{"id":168,"isocode2":"NO"}},{"id":2620,"name":"Vestfold","country":{"id":168,"isocode2":"NO"}},{"id":2621,"name":"ÃƒÂ˜stfold","country":{"id":168,"isocode2":"NO"}}]